{
  "id": "shot_006_13",
  "scene": "scene_006",
  "order": 13,
  "characters": [
    "renna_ashfall_scavenger",
    "kaelen_scarred_architect"
  ],
  "image_prompt": "1girl, short messy brown hair, wary amber eyes, wiry build, ragged cloak, fingerless gloves, leather bracers, multiple utility pouches, scavenging tools, dirt on face, survivalist, 1boy, short black hair, sharp grey eyes, lean muscular build, multiple scars, worn dark leather armor, practical clothing, gauntlets, cold expression, battle-worn, The Ashfall Wastes, A desolate, windswept region choked by the perpetual dust and debris of ancient conflicts, marked by skeletal ruins and scarce resources. This harsh frontier serves as the lowest rung of society, a brutal proving ground where only the most determined survive., Renna looks from the dead strongman to the silent, imposing figure of Kaelen., masterpiece, best quality, cel shading, bold outlines, vibrant saturated colors, anime screencap",
  "image_prompt_end": "",
  "needs_end_frame": false,
  "motion_prompt": "Renna looks from the dead strongman to the silent, imposing figure of Kaelen.; Medium close-up, Renna's gaze shifts from off-screen (strongman) to Kaelen.",
  "dialogue": [],
  "seed": null,
  "duration_s": 4.0,
  "status": {
    "keyframe": "pending",
    "clip": "pending",
    "audio": "pending"
  },
  "assets": {
    "keyframe": null,
    "keyframe_end": null,
    "clip": null,
    "audio": null
  },
  "provider": {
    "art": null,
    "animate": null
  }
}
